.gitignore
CMakeLists.txt
LICENSE
MANIFEST.in
README.md
pyproject.toml
requirements.txt
setup.py
.idea/.gitignore
.idea/encodings.xml
.idea/misc.xml
.idea/modules.xml
.idea/vcs.xml
.idea/webResources.xml
.vscode/settings.json
docs/guide.md
docs/vanilla.md
examples/5m1c.s
examples/5m1c.v
examples/5r8c.s
examples/5r8c.v
examples/6e1c.v
examples/6m1c.s
examples/6m1c.v
examples/6m2r.v
examples/6m2r2c.s
examples/6m2r2c.v
examples/6r1b.cmd
examples/6r1b.s
examples/6r1b.v
examples/6r1c.s
examples/6r1c.v
examples/6t1c.v
examples/6t2r.v
examples/DataFormat
examples/d2.s
examples/d2.v
examples/d2r3m6.s
examples/d2r3m6.v
examples/dr3m6
examples/phi.cmd
examples/phi.log
examples/phi.s
examples/phi.v
examples/sd1.s
examples/sd1.v
examples/sst.csv
examples/test.cmd
examples/test.log
examples/vm.cmd
examples/vm.log
examples/vm.s
examples/vm.v
examples/vmd.s
examples/wholesale.csv
examples/xrf.csv
examples/xrf.s
examples/xrf.v
examples/zfish-bioxas-ds.csv
snob/__init__.py
snob/example.py
snob/example2.py
snob/example3.py
snob/example4.py
snob_factor.egg-info/PKG-INFO
snob_factor.egg-info/SOURCES.txt
snob_factor.egg-info/dependency_links.txt
snob_factor.egg-info/requires.txt
snob_factor.egg-info/top_level.txt
src/Makefile
src/badmoves.c
src/block.c
src/classes.c
src/doall.c
src/dotypes.c
src/expbin.c
src/expmults.c
src/glob.c
src/glob.h
src/inputs.c
src/listen.c
src/main.c
src/poplns.c
src/prompt.c
src/reals.c
src/samples.c
src/snob.c
src/snob.h
src/tactics.c
src/tune.c
src/vmtabs.c
src/vonm.c
src/snob.egg-info/PKG-INFO
src/snob.egg-info/SOURCES.txt
src/snob.egg-info/dependency_links.txt
src/snob.egg-info/requires.txt
src/snob.egg-info/top_level.txt
tests/test.sh