Metadata-Version: 2.1
Name: snob-factor
Version: 2024.2.4
Summary: Mixture modelling by Minimum Message Length (MML) using Factor Snob
Author-email: Chris Wallace <csw@cs.monash.edu.au>, Michel Fodje <michel.fodje@lightsource.ca>
Maintainer-email: Michel Fodje <michel.fodje@lightsource.ca>
License:                     GNU GENERAL PUBLIC LICENSE
Project-URL: Homepage, https://github.com/michel4j/snob-factor
Project-URL: documentation, https://github.com/michel4j/snob-factor
Project-URL: repository, https://github.com/michel4j/snob-factor
Keywords: MML,Unsupervised Classification,Machine Learning,Snob,Factor Analysis
Classifier: Intended Audience :: Science/Research
Classifier: Intended Audience :: Developers
Classifier: Topic :: Scientific/Engineering :: Artificial Intelligence
Classifier: License :: OSI Approved :: GNU General Public License v3 (GPLv3)
Classifier: Natural Language :: English
Classifier: Programming Language :: C
Classifier: Programming Language :: Python :: 3
Classifier: Operating System :: OS Independent
Requires-Python: >=3.7.5
License-File: LICENSE
Requires-Dist: pandas
Requires-Dist: numpy
